euler/__init__.py
euler/prime.py
euler/tests/__init__.py
euler/tests/test_prime.py
project_euler_helpers-0.0.2.dist-info/METADATA
project_euler_helpers-0.0.2.dist-info/WHEEL
project_euler_helpers-0.0.2.dist-info/top_level.txt
project_euler_helpers-0.0.2.dist-info/RECORD
