Metadata-Version: 2.1
Name: project-euler-helpers
Version: 0.0.2
Summary: Helper functions for solving Project Euler Problems, in Python.
Home-page: https://github.com/aahnik/
Author: Aahnik Daw
Author-email: meet.aahnik@gmail.com
License: UNKNOWN
Platform: UNKNOWN
Classifier: Programming Language :: Python :: 3
Classifier: License :: OSI Approved :: MIT License
Classifier: Operating System :: OS Independent
Requires-Python: >=3.6
